mahdi/__init__.py
Mahdihh-0.1.dist-info/METADATA
Mahdihh-0.1.dist-info/WHEEL
Mahdihh-0.1.dist-info/top_level.txt
Mahdihh-0.1.dist-info/RECORD
